MANIFEST.in
requirements.txt
setup.py
flask_app_generator.egg-info/PKG-INFO
flask_app_generator.egg-info/SOURCES.txt
flask_app_generator.egg-info/dependency_links.txt
flask_app_generator.egg-info/entry_points.txt
flask_app_generator.egg-info/requires.txt
flask_app_generator.egg-info/top_level.txt
src/__init__.py
src/flask_app_generator/__init__.py
src/flask_app_generator/exceptions.py
src/flask_app_generator/generator.py
src/flask_app_generator/run.py
src/flask_app_generator/urls.py
src/flask_app_generator/config/__init__.py
src/flask_app_generator/config/dev.py.j2
src/flask_app_generator/config/prod.py.j2
src/flask_app_generator/templates/.gitignore
src/flask_app_generator/templates/README.md.j2
src/flask_app_generator/templates/__init__.py
src/flask_app_generator/templates/app_large.py
src/flask_app_generator/templates/app_simple.py
src/flask_app_generator/templates/manage.py
src/flask_app_generator/templates/requirements.txt
src/flask_app_generator/templates/html/index.html
src/flask_app_generator/templates/html/layout.html
src/flask_app_generator/templates/views/__init__.py
src/flask_app_generator/templates/views/index.py