Metadata-Version: 1.0
Name: flask-app-generator
Version: 0.1.0
Summary: Flask Project Generator
Home-page: https://github.com/SeoDongMyeong/flask-app-generator
Author: ClaudeSeo
Author-email: ehdaudtj@gmail.com
License: MIT License
Keywords: flask,flask-project,flask-generator
Platform: UNKNOWN
